{
  "id": "1598348",
  "name": "OA系统图标库",
  "font_family": "iconfont",
  "css_prefix_text": "icon-",
  "description": "",
  "glyphs": [
    {
      "icon_id": "5084",
      "name": "百度 方形",
      "font_class": "baidufangxing",
      "unicode": "e679",
      "unicode_decimal": 59001
    },
    {
      "icon_id": "11190",
      "name": "分页 最后页",
      "font_class": "fenyezuihouye",
      "unicode": "e603",
      "unicode_decimal": 58883
    },
    {
      "icon_id": "11191",
      "name": "分页 最前页",
      "font_class": "fenyezuiqianye",
      "unicode": "e604",
      "unicode_decimal": 58884
    },
    {
      "icon_id": "13198",
      "name": "钻石",
      "font_class": "zuanshi",
      "unicode": "e6d6",
      "unicode_decimal": 59094
    },
    {
      "icon_id": "40918",
      "name": "位置",
      "font_class": "weizhi",
      "unicode": "e6d7",
      "unicode_decimal": 59095
    },
    {
      "icon_id": "59567",
      "name": "恢复",
      "font_class": "iconfontqianjin",
      "unicode": "e65f",
      "unicode_decimal": 58975
    },
    {
      "icon_id": "74433",
      "name": "qq",
      "font_class": "qq",
      "unicode": "e82e",
      "unicode_decimal": 59438
    },
    {
      "icon_id": "81664",
      "name": "上传",
      "font_class": "shangchuan",
      "unicode": "e6d8",
      "unicode_decimal": 59096
    },
    {
      "icon_id": "83694",
      "name": "停止",
      "font_class": "stop",
      "unicode": "e6d9",
      "unicode_decimal": 59097
    },
    {
      "icon_id": "106755",
      "name": "加载",
      "font_class": "load",
      "unicode": "e6da",
      "unicode_decimal": 59098
    },
    {
      "icon_id": "138613",
      "name": "女",
      "font_class": "nv",
      "unicode": "e6ba",
      "unicode_decimal": 59066
    },
    {
      "icon_id": "143666",
      "name": "下载",
      "font_class": "ddd",
      "unicode": "e6db",
      "unicode_decimal": 59099
    },
    {
      "icon_id": "158663",
      "name": "百度",
      "font_class": "baidu",
      "unicode": "e67a",
      "unicode_decimal": 59002
    },
    {
      "icon_id": "236037",
      "name": "货币",
      "font_class": "dk",
      "unicode": "e6dd",
      "unicode_decimal": 59101
    },
    {
      "icon_id": "286354",
      "name": "用户",
      "font_class": "yonghu",
      "unicode": "e6cb",
      "unicode_decimal": 59083
    },
    {
      "icon_id": "321614",
      "name": "分享",
      "font_class": "fenxiang",
      "unicode": "e6e1",
      "unicode_decimal": 59105
    },
    {
      "icon_id": "339614",
      "name": "组件",
      "font_class": "zujian",
      "unicode": "e6e2",
      "unicode_decimal": 59106
    },
    {
      "icon_id": "357572",
      "name": "提示",
      "font_class": "tishi",
      "unicode": "e680",
      "unicode_decimal": 59008
    },
    {
      "icon_id": "366107",
      "name": "验证码",
      "font_class": "yanzhengma",
      "unicode": "e654",
      "unicode_decimal": 58964
    },
    {
      "icon_id": "376214",
      "name": "阅读",
      "font_class": "yuedu",
      "unicode": "e6e4",
      "unicode_decimal": 59108
    },
    {
      "icon_id": "512193",
      "name": "链接",
      "font_class": "iconfont",
      "unicode": "e6e5",
      "unicode_decimal": 59109
    },
    {
      "icon_id": "513836",
      "name": "查找 定位",
      "font_class": "iconfind",
      "unicode": "e6e6",
      "unicode_decimal": 59110
    },
    {
      "icon_id": "525711",
      "name": "阅读",
      "font_class": "yuedu1",
      "unicode": "e6e7",
      "unicode_decimal": 59111
    },
    {
      "icon_id": "538222",
      "name": "钻石",
      "font_class": "zuanshi1",
      "unicode": "e6e8",
      "unicode_decimal": 59112
    },
    {
      "icon_id": "538489",
      "name": "加",
      "font_class": "jia",
      "unicode": "e6a3",
      "unicode_decimal": 59043
    },
    {
      "icon_id": "556126",
      "name": "手机",
      "font_class": "shouji",
      "unicode": "e62c",
      "unicode_decimal": 58924
    },
    {
      "icon_id": "567953",
      "name": "手机",
      "font_class": "shouji1",
      "unicode": "e6b0",
      "unicode_decimal": 59056
    },
    {
      "icon_id": "597318",
      "name": "成功",
      "font_class": "chenggong",
      "unicode": "e6bf",
      "unicode_decimal": 59071
    },
    {
      "icon_id": "600919",
      "name": "菜单",
      "font_class": "caidan",
      "unicode": "e665",
      "unicode_decimal": 58981
    },
    {
      "icon_id": "604757",
      "name": "刷新",
      "font_class": "shuaxin",
      "unicode": "e786",
      "unicode_decimal": 59270
    },
    {
      "icon_id": "655162",
      "name": "踩",
      "font_class": "cai",
      "unicode": "e6b2",
      "unicode_decimal": 59058
    },
    {
      "icon_id": "686465",
      "name": "提示",
      "font_class": "tishi1",
      "unicode": "e681",
      "unicode_decimal": 59009
    },
    {
      "icon_id": "686676",
      "name": "乘1_线",
      "font_class": "cheng1xian",
      "unicode": "e7dd",
      "unicode_decimal": 59357
    },
    {
      "icon_id": "687898",
      "name": "搜索",
      "font_class": "iconserch01",
      "unicode": "e6e9",
      "unicode_decimal": 59113
    },
    {
      "icon_id": "688137",
      "name": "用户 访客数",
      "font_class": "yonghufangkeshu",
      "unicode": "e7ad",
      "unicode_decimal": 59309
    },
    {
      "icon_id": "741121",
      "name": "分页-01",
      "font_class": "prev-arrow",
      "unicode": "e60a",
      "unicode_decimal": 58890
    },
    {
      "icon_id": "741122",
      "name": "分页-02",
      "font_class": "next-arrow",
      "unicode": "e60b",
      "unicode_decimal": 58891
    },
    {
      "icon_id": "746190",
      "name": "成功",
      "font_class": "chenggong6",
      "unicode": "e7bf",
      "unicode_decimal": 59327
    },
    {
      "icon_id": "776141",
      "name": "赞",
      "font_class": "zan",
      "unicode": "e6de",
      "unicode_decimal": 59102
    },
    {
      "icon_id": "812466",
      "name": "货币兑换",
      "font_class": "huobiduihuan",
      "unicode": "e6ea",
      "unicode_decimal": 59114
    },
    {
      "icon_id": "825012",
      "name": "锁",
      "font_class": "unlocked2",
      "unicode": "e64b",
      "unicode_decimal": 58955
    },
    {
      "icon_id": "934724",
      "name": "上传",
      "font_class": "shangchuan1",
      "unicode": "e6eb",
      "unicode_decimal": 59115
    },
    {
      "icon_id": "1062293",
      "name": "赞",
      "font_class": "zan1",
      "unicode": "e6b3",
      "unicode_decimal": 59059
    },
    {
      "icon_id": "1094483",
      "name": "减",
      "font_class": "reduce",
      "unicode": "e6b4",
      "unicode_decimal": 59060
    },
    {
      "icon_id": "1181444",
      "name": "百度",
      "font_class": "baidu1",
      "unicode": "e67d",
      "unicode_decimal": 59005
    },
    {
      "icon_id": "1220706",
      "name": "手机",
      "font_class": "shouji2",
      "unicode": "e62d",
      "unicode_decimal": 58925
    },
    {
      "icon_id": "1233052",
      "name": "男",
      "font_class": "nan",
      "unicode": "e6bb",
      "unicode_decimal": 59067
    },
    {
      "icon_id": "1260982",
      "name": "用户删除",
      "font_class": "yonghushanchu",
      "unicode": "e645",
      "unicode_decimal": 58949
    },
    {
      "icon_id": "1297884",
      "name": "链接",
      "font_class": "lianjie",
      "unicode": "e6ec",
      "unicode_decimal": 59116
    },
    {
      "icon_id": "1355883",
      "name": "上传",
      "font_class": "shangchuan2",
      "unicode": "e6ee",
      "unicode_decimal": 59118
    },
    {
      "icon_id": "1364843",
      "name": "分页-右",
      "font_class": "right-circle",
      "unicode": "e66e",
      "unicode_decimal": 58990
    },
    {
      "icon_id": "1364850",
      "name": "分页-左",
      "font_class": "left-circle",
      "unicode": "e66f",
      "unicode_decimal": 58991
    },
    {
      "icon_id": "1380652",
      "name": "相机",
      "font_class": "xiangji",
      "unicode": "e6ef",
      "unicode_decimal": 59119
    },
    {
      "icon_id": "1382062",
      "name": "货币兑换",
      "font_class": "huobiduihuan1",
      "unicode": "e6f0",
      "unicode_decimal": 59120
    },
    {
      "icon_id": "1382584",
      "name": "微信 (1)",
      "font_class": "weixin",
      "unicode": "e659",
      "unicode_decimal": 58969
    },
    {
      "icon_id": "1384143",
      "name": "qq",
      "font_class": "qq1",
      "unicode": "e642",
      "unicode_decimal": 58946
    },
    {
      "icon_id": "1389419",
      "name": "隐藏",
      "font_class": "hidden",
      "unicode": "e6f1",
      "unicode_decimal": 59121
    },
    {
      "icon_id": "1409040",
      "name": "编辑",
      "font_class": "bianji",
      "unicode": "e6f2",
      "unicode_decimal": 59122
    },
    {
      "icon_id": "1465251",
      "name": "搜索",
      "font_class": "sousuo",
      "unicode": "e6f3",
      "unicode_decimal": 59123
    },
    {
      "icon_id": "1472532",
      "name": "加",
      "font_class": "jia1",
      "unicode": "e6a4",
      "unicode_decimal": 59044
    },
    {
      "icon_id": "1473715",
      "name": "货币",
      "font_class": "huobi",
      "unicode": "e6f4",
      "unicode_decimal": 59124
    },
    {
      "icon_id": "1502917",
      "name": "微信",
      "font_class": "weixin1",
      "unicode": "e63f",
      "unicode_decimal": 58943
    },
    {
      "icon_id": "1503397",
      "name": "分页 最前页",
      "font_class": "first-blue",
      "unicode": "e605",
      "unicode_decimal": 58885
    },
    {
      "icon_id": "1521409",
      "name": "半星",
      "font_class": "star-half-blk",
      "unicode": "e61c",
      "unicode_decimal": 58908
    },
    {
      "icon_id": "1524961",
      "name": "微信",
      "font_class": "weixin2",
      "unicode": "e640",
      "unicode_decimal": 58944
    },
    {
      "icon_id": "1539710",
      "name": "加",
      "font_class": "jia2",
      "unicode": "e6a5",
      "unicode_decimal": 59045
    },
    {
      "icon_id": "1566273",
      "name": "女",
      "font_class": "woman",
      "unicode": "e6bc",
      "unicode_decimal": 59068
    },
    {
      "icon_id": "1575557",
      "name": "微信",
      "font_class": "weixin3",
      "unicode": "e938",
      "unicode_decimal": 59704
    },
    {
      "icon_id": "1617264",
      "name": "编辑",
      "font_class": "bianji1",
      "unicode": "e6f5",
      "unicode_decimal": 59125
    },
    {
      "icon_id": "1631906",
      "name": "货币_美元",
      "font_class": "huobi_meiyuan",
      "unicode": "e9fc",
      "unicode_decimal": 59900
    },
    {
      "icon_id": "1651657",
      "name": "分页栏_任务_实心",
      "font_class": "flag-shixin",
      "unicode": "e606",
      "unicode_decimal": 58886
    },
    {
      "icon_id": "1651660",
      "name": "分页栏_应用_实心",
      "font_class": "yingyong-shixin",
      "unicode": "e607",
      "unicode_decimal": 58887
    },
    {
      "icon_id": "1651662",
      "name": "分页栏_主页_实心",
      "font_class": "home-shixin",
      "unicode": "e609",
      "unicode_decimal": 58889
    },
    {
      "icon_id": "1651664",
      "name": "分页栏_应用_空心",
      "font_class": "yingyong-kongxin",
      "unicode": "e60c",
      "unicode_decimal": 58892
    },
    {
      "icon_id": "1651668",
      "name": "分页栏_主页_空心",
      "font_class": "home-kongxin",
      "unicode": "e60d",
      "unicode_decimal": 58893
    },
    {
      "icon_id": "1665542",
      "name": "水",
      "font_class": "shui",
      "unicode": "e6f6",
      "unicode_decimal": 59126
    },
    {
      "icon_id": "1678695",
      "name": "减",
      "font_class": "jian",
      "unicode": "e6a6",
      "unicode_decimal": 59046
    },
    {
      "icon_id": "1694034",
      "name": "编辑",
      "font_class": "bianji-blue",
      "unicode": "e6f7",
      "unicode_decimal": 59127
    },
    {
      "icon_id": "1698546",
      "name": "货币",
      "font_class": "ic_local_atm_px",
      "unicode": "e70f",
      "unicode_decimal": 59151
    },
    {
      "icon_id": "1707983",
      "name": "微博",
      "font_class": "weibo",
      "unicode": "e644",
      "unicode_decimal": 58948
    },
    {
      "icon_id": "1713497",
      "name": "成功",
      "font_class": "chenggong1",
      "unicode": "e698",
      "unicode_decimal": 59032
    },
    {
      "icon_id": "1719301",
      "name": "微信 (1)",
      "font_class": "weixin4",
      "unicode": "e7b4",
      "unicode_decimal": 59316
    },
    {
      "icon_id": "1749777",
      "name": "编辑",
      "font_class": "bianji2",
      "unicode": "e6f8",
      "unicode_decimal": 59128
    },
    {
      "icon_id": "1818656",
      "name": "微信 (1)",
      "font_class": "weixin5",
      "unicode": "e641",
      "unicode_decimal": 58945
    },
    {
      "icon_id": "1855669",
      "name": "手机",
      "font_class": "phone",
      "unicode": "e62f",
      "unicode_decimal": 58927
    },
    {
      "icon_id": "1875895",
      "name": "失败",
      "font_class": "shibai",
      "unicode": "e69e",
      "unicode_decimal": 59038
    },
    {
      "icon_id": "1894060",
      "name": "钻石",
      "font_class": "zuanshi2",
      "unicode": "e6f9",
      "unicode_decimal": 59129
    },
    {
      "icon_id": "1925365",
      "name": "用户",
      "font_class": "iconfontcolor19-copy",
      "unicode": "e646",
      "unicode_decimal": 58950
    },
    {
      "icon_id": "1973125",
      "name": "踩",
      "font_class": "dislike__easy",
      "unicode": "e6b5",
      "unicode_decimal": 59061
    },
    {
      "icon_id": "2011689",
      "name": "失败",
      "font_class": "shibai1",
      "unicode": "e6a1",
      "unicode_decimal": 59041
    },
    {
      "icon_id": "2099187",
      "name": "手机  ",
      "font_class": "shouji3",
      "unicode": "e631",
      "unicode_decimal": 58929
    },
    {
      "icon_id": "2124513",
      "name": "图片下载",
      "font_class": "tupianxiazai",
      "unicode": "e6fa",
      "unicode_decimal": 59130
    },
    {
      "icon_id": "2203701",
      "name": "女",
      "font_class": "woman1",
      "unicode": "e6bd",
      "unicode_decimal": 59069
    },
    {
      "icon_id": "2211326",
      "name": "上传",
      "font_class": "shangchuan3",
      "unicode": "e6fb",
      "unicode_decimal": 59131
    },
    {
      "icon_id": "2298438",
      "name": "乘",
      "font_class": "cheng",
      "unicode": "e6e3",
      "unicode_decimal": 59107
    },
    {
      "icon_id": "2348618",
      "name": "刷新",
      "font_class": "shuaxin1",
      "unicode": "e653",
      "unicode_decimal": 58963
    },
    {
      "icon_id": "2366078",
      "name": "女",
      "font_class": "nannv",
      "unicode": "e94a",
      "unicode_decimal": 59722
    },
    {
      "icon_id": "2380637",
      "name": "购物车",
      "font_class": "gouwuche",
      "unicode": "e6fc",
      "unicode_decimal": 59132
    },
    {
      "icon_id": "2386121",
      "name": "分页 下一页",
      "font_class": "pagernext-blk",
      "unicode": "e60e",
      "unicode_decimal": 58894
    },
    {
      "icon_id": "2430934",
      "name": "耳机",
      "font_class": "erji",
      "unicode": "e6fd",
      "unicode_decimal": 59133
    },
    {
      "icon_id": "2442459",
      "name": "货币",
      "font_class": "huobi1",
      "unicode": "e6fe",
      "unicode_decimal": 59134
    },
    {
      "icon_id": "2479428",
      "name": "请假",
      "font_class": "qingjia",
      "unicode": "e799",
      "unicode_decimal": 59289
    },
    {
      "icon_id": "2488391",
      "name": "位置",
      "font_class": "weizhi1",
      "unicode": "e6ff",
      "unicode_decimal": 59135
    },
    {
      "icon_id": "2491253",
      "name": "半星",
      "font_class": "star-half-blue",
      "unicode": "e73f",
      "unicode_decimal": 59199
    },
    {
      "icon_id": "2494668",
      "name": "用户删除",
      "font_class": "1",
      "unicode": "e647",
      "unicode_decimal": 58951
    },
    {
      "icon_id": "2649879",
      "name": "菜单",
      "font_class": "menu",
      "unicode": "e667",
      "unicode_decimal": 58983
    },
    {
      "icon_id": "2653428",
      "name": "菜单",
      "font_class": "caidan1",
      "unicode": "e668",
      "unicode_decimal": 58984
    },
    {
      "icon_id": "2737414",
      "name": "上传",
      "font_class": "shangchuan4",
      "unicode": "e7ae",
      "unicode_decimal": 59310
    },
    {
      "icon_id": "2827547",
      "name": "男",
      "font_class": "nan1",
      "unicode": "e6be",
      "unicode_decimal": 59070
    },
    {
      "icon_id": "2858051",
      "name": "撤回",
      "font_class": "chehui",
      "unicode": "e660",
      "unicode_decimal": 58976
    },
    {
      "icon_id": "2909672",
      "name": "编辑",
      "font_class": "bianji3",
      "unicode": "e700",
      "unicode_decimal": 59136
    },
    {
      "icon_id": "2913266",
      "name": "链接",
      "font_class": "lianjie1",
      "unicode": "e701",
      "unicode_decimal": 59137
    },
    {
      "icon_id": "2986427",
      "name": "搜索--1",
      "font_class": "search",
      "unicode": "e702",
      "unicode_decimal": 59138
    },
    {
      "icon_id": "2988429",
      "name": "菜单",
      "font_class": "caidan2",
      "unicode": "e669",
      "unicode_decimal": 58985
    },
    {
      "icon_id": "3001766",
      "name": "赞",
      "font_class": "zan2",
      "unicode": "e6b6",
      "unicode_decimal": 59062
    },
    {
      "icon_id": "3003657",
      "name": "星星",
      "font_class": "star-red",
      "unicode": "e622",
      "unicode_decimal": 58914
    },
    {
      "icon_id": "3010568",
      "name": "分页 上一页",
      "font_class": "pagernext-blue",
      "unicode": "e60f",
      "unicode_decimal": 58895
    },
    {
      "icon_id": "3169987",
      "name": "雪花",
      "font_class": "xuehua",
      "unicode": "e676",
      "unicode_decimal": 58998
    },
    {
      "icon_id": "3195426",
      "name": "WIFI 我fi",
      "font_class": "WIFIwofi",
      "unicode": "e704",
      "unicode_decimal": 59140
    },
    {
      "icon_id": "3199648",
      "name": "百度",
      "font_class": "baidu2",
      "unicode": "e67e",
      "unicode_decimal": 59006
    },
    {
      "icon_id": "3229597",
      "name": "链接",
      "font_class": "lianjie2",
      "unicode": "e705",
      "unicode_decimal": 59141
    },
    {
      "icon_id": "3264114",
      "name": "暂停",
      "font_class": "button",
      "unicode": "e706",
      "unicode_decimal": 59142
    },
    {
      "icon_id": "3296988",
      "name": "提示",
      "font_class": "tishi2",
      "unicode": "e682",
      "unicode_decimal": 59010
    },
    {
      "icon_id": "3305161",
      "name": "货币",
      "font_class": "huobi2",
      "unicode": "e707",
      "unicode_decimal": 59143
    },
    {
      "icon_id": "3305372",
      "name": "除",
      "font_class": "chu",
      "unicode": "e6a7",
      "unicode_decimal": 59047
    },
    {
      "icon_id": "3327112",
      "name": "链接",
      "font_class": "lianjie3",
      "unicode": "ea54",
      "unicode_decimal": 59988
    },
    {
      "icon_id": "3359317",
      "name": "隐藏",
      "font_class": "yincang",
      "unicode": "e708",
      "unicode_decimal": 59144
    },
    {
      "icon_id": "3390160",
      "name": "位置",
      "font_class": "weizhi2",
      "unicode": "e709",
      "unicode_decimal": 59145
    },
    {
      "icon_id": "3398344",
      "name": "用户修改",
      "font_class": "yonghuxiugai",
      "unicode": "e657",
      "unicode_decimal": 58967
    },
    {
      "icon_id": "3398346",
      "name": "用户修改-线性",
      "font_class": "yonghuxiugai-xianxing",
      "unicode": "e658",
      "unicode_decimal": 58968
    },
    {
      "icon_id": "3408381",
      "name": "减",
      "font_class": "jian1",
      "unicode": "e756",
      "unicode_decimal": 59222
    },
    {
      "icon_id": "3417684",
      "name": "钻石",
      "font_class": "zuanshi3",
      "unicode": "e70a",
      "unicode_decimal": 59146
    },
    {
      "icon_id": "3427899",
      "name": "提示",
      "font_class": "tishi3",
      "unicode": "e683",
      "unicode_decimal": 59011
    },
    {
      "icon_id": "3465188",
      "name": "提示",
      "font_class": "tishi4",
      "unicode": "e684",
      "unicode_decimal": 59012
    },
    {
      "icon_id": "3511323",
      "name": "停止",
      "font_class": "tingzhi",
      "unicode": "e93d",
      "unicode_decimal": 59709
    },
    {
      "icon_id": "3524311",
      "name": "分页 下一页",
      "font_class": "pagerprev-blue",
      "unicode": "e610",
      "unicode_decimal": 58896
    },
    {
      "icon_id": "3524315",
      "name": "分页 最后页",
      "font_class": "last-blue",
      "unicode": "e612",
      "unicode_decimal": 58898
    },
    {
      "icon_id": "3525030",
      "name": "暂停",
      "font_class": "zanting",
      "unicode": "e70c",
      "unicode_decimal": 59148
    },
    {
      "icon_id": "3526713",
      "name": "失败",
      "font_class": "shibai2",
      "unicode": "e6a2",
      "unicode_decimal": 59042
    },
    {
      "icon_id": "3530442",
      "name": "提示",
      "font_class": "tishi5",
      "unicode": "e685",
      "unicode_decimal": 59013
    },
    {
      "icon_id": "3642544",
      "name": "提示",
      "font_class": "tishi6",
      "unicode": "e686",
      "unicode_decimal": 59014
    },
    {
      "icon_id": "3663481",
      "name": "验证码",
      "font_class": "yanzhengma1",
      "unicode": "e65a",
      "unicode_decimal": 58970
    },
    {
      "icon_id": "3725011",
      "name": "用户",
      "font_class": "yonghu1",
      "unicode": "e6c7",
      "unicode_decimal": 59079
    },
    {
      "icon_id": "3730050",
      "name": "用户",
      "font_class": "yonghu2",
      "unicode": "e648",
      "unicode_decimal": 58952
    },
    {
      "icon_id": "3776052",
      "name": "乘",
      "font_class": "cheng1",
      "unicode": "e6a8",
      "unicode_decimal": 59048
    },
    {
      "icon_id": "3776053",
      "name": "除",
      "font_class": "chu1",
      "unicode": "e6a9",
      "unicode_decimal": 59049
    },
    {
      "icon_id": "3865267",
      "name": "查找",
      "font_class": "chazhao",
      "unicode": "e70d",
      "unicode_decimal": 59149
    },
    {
      "icon_id": "3872515",
      "name": "用户",
      "font_class": "yonghu3",
      "unicode": "e649",
      "unicode_decimal": 58953
    },
    {
      "icon_id": "3882767",
      "name": "验证码",
      "font_class": "yanzhengma2",
      "unicode": "e632",
      "unicode_decimal": 58930
    },
    {
      "icon_id": "3893254",
      "name": "个人信息",
      "font_class": "gerenxinxi",
      "unicode": "e611",
      "unicode_decimal": 58897
    },
    {
      "icon_id": "3983852",
      "name": "艾特",
      "font_class": "aite",
      "unicode": "e634",
      "unicode_decimal": 58932
    },
    {
      "icon_id": "4058241",
      "name": "copyright",
      "font_class": "uniE",
      "unicode": "e616",
      "unicode_decimal": 58902
    },
    {
      "icon_id": "4094025",
      "name": "lock",
      "font_class": "unlocked3",
      "unicode": "e63a",
      "unicode_decimal": 58938
    },
    {
      "icon_id": "4099311",
      "name": "lock",
      "font_class": "locked3",
      "unicode": "ee4f",
      "unicode_decimal": 61007
    },
    {
      "icon_id": "4158236",
      "name": "相机",
      "font_class": "xiangji1",
      "unicode": "e70e",
      "unicode_decimal": 59150
    },
    {
      "icon_id": "4169819",
      "name": "在线反馈",
      "font_class": "icon1",
      "unicode": "e601",
      "unicode_decimal": 58881
    },
    {
      "icon_id": "4189147",
      "name": "分 享",
      "font_class": "fenxiang-copy",
      "unicode": "e8bc",
      "unicode_decimal": 59580
    },
    {
      "icon_id": "4196704",
      "name": "系统",
      "font_class": "duoxitong",
      "unicode": "e61d",
      "unicode_decimal": 58909
    },
    {
      "icon_id": "4211490",
      "name": "女",
      "font_class": "nv1",
      "unicode": "e6c0",
      "unicode_decimal": 59072
    },
    {
      "icon_id": "4211491",
      "name": "男",
      "font_class": "nan2",
      "unicode": "e6c1",
      "unicode_decimal": 59073
    },
    {
      "icon_id": "4258121",
      "name": "Wifi",
      "font_class": "Wifi",
      "unicode": "e710",
      "unicode_decimal": 59152
    },
    {
      "icon_id": "4270382",
      "name": "眼睛",
      "font_class": "yanjing",
      "unicode": "e711",
      "unicode_decimal": 59153
    },
    {
      "icon_id": "4300489",
      "name": "刷新",
      "font_class": "shuaxin2",
      "unicode": "e655",
      "unicode_decimal": 58965
    },
    {
      "icon_id": "4373443",
      "name": "雪花",
      "font_class": "xuehua1",
      "unicode": "e677",
      "unicode_decimal": 58999
    },
    {
      "icon_id": "4392731",
      "name": "停止",
      "font_class": "tingzhi1",
      "unicode": "e712",
      "unicode_decimal": 59154
    },
    {
      "icon_id": "4412090",
      "name": "组件",
      "font_class": "zujian1",
      "unicode": "e847",
      "unicode_decimal": 59463
    },
    {
      "icon_id": "4438639",
      "name": "验证码",
      "font_class": "yanzhengma3",
      "unicode": "e6a0",
      "unicode_decimal": 59040
    },
    {
      "icon_id": "4486785",
      "name": "除",
      "font_class": "chu2",
      "unicode": "e6aa",
      "unicode_decimal": 59050
    },
    {
      "icon_id": "4499136",
      "name": "赞",
      "font_class": "like__easyico",
      "unicode": "e6b7",
      "unicode_decimal": 59063
    },
    {
      "icon_id": "4547848",
      "name": "男",
      "font_class": "msnui-male",
      "unicode": "e6c2",
      "unicode_decimal": 59074
    },
    {
      "icon_id": "4582542",
      "name": "用户锁定",
      "font_class": "yonghusuoding",
      "unicode": "e69f",
      "unicode_decimal": 59039
    },
    {
      "icon_id": "4592383",
      "name": "报销流程",
      "font_class": "baoxiaoliucheng",
      "unicode": "e628",
      "unicode_decimal": 58920
    },
    {
      "icon_id": "4602098",
      "name": "用户",
      "font_class": "user",
      "unicode": "e64a",
      "unicode_decimal": 58954
    },
    {
      "icon_id": "4602543",
      "name": "百分号",
      "font_class": "baifenhao",
      "unicode": "e6ac",
      "unicode_decimal": 59052
    },
    {
      "icon_id": "4658202",
      "name": "验证码",
      "font_class": "yanzhengma4",
      "unicode": "e633",
      "unicode_decimal": 58931
    },
    {
      "icon_id": "4750155",
      "name": "位置",
      "font_class": "weizhi3",
      "unicode": "e714",
      "unicode_decimal": 59156
    },
    {
      "icon_id": "4762796",
      "name": "星星",
      "font_class": "star-line-red",
      "unicode": "e623",
      "unicode_decimal": 58915
    },
    {
      "icon_id": "4822335",
      "name": "禁止拍照",
      "font_class": "jinzhipaizhao",
      "unicode": "e715",
      "unicode_decimal": 59157
    },
    {
      "icon_id": "4846104",
      "name": "暂停",
      "font_class": "zanting1",
      "unicode": "e85e",
      "unicode_decimal": 59486
    },
    {
      "icon_id": "4886084",
      "name": "水",
      "font_class": "shui1",
      "unicode": "e716",
      "unicode_decimal": 59158
    },
    {
      "icon_id": "4933171",
      "name": "提示",
      "font_class": "tishi7",
      "unicode": "e6d1",
      "unicode_decimal": 59089
    },
    {
      "icon_id": "4933410",
      "name": "提示",
      "font_class": "tishi8",
      "unicode": "e75a",
      "unicode_decimal": 59226
    },
    {
      "icon_id": "4991144",
      "name": "验证码",
      "font_class": "yanzhengma5",
      "unicode": "e635",
      "unicode_decimal": 58933
    },
    {
      "icon_id": "5004123",
      "name": "请假",
      "font_class": "qingjia1",
      "unicode": "e64e",
      "unicode_decimal": 58958
    },
    {
      "icon_id": "5114466",
      "name": "加载",
      "font_class": "jiazai",
      "unicode": "e717",
      "unicode_decimal": 59159
    },
    {
      "icon_id": "5131439",
      "name": "加载",
      "font_class": "jiazai1",
      "unicode": "e718",
      "unicode_decimal": 59160
    },
    {
      "icon_id": "5138343",
      "name": "加载",
      "font_class": "jiazai2",
      "unicode": "eabc",
      "unicode_decimal": 60092
    },
    {
      "icon_id": "5159225",
      "name": "提示",
      "font_class": "tishi9",
      "unicode": "e687",
      "unicode_decimal": 59015
    },
    {
      "icon_id": "5264140",
      "name": "加载",
      "font_class": "jiazai3",
      "unicode": "e719",
      "unicode_decimal": 59161
    },
    {
      "icon_id": "5280189",
      "name": "提示",
      "font_class": "tishi10",
      "unicode": "e97d",
      "unicode_decimal": 59773
    },
    {
      "icon_id": "5284581",
      "name": "男",
      "font_class": "nan3",
      "unicode": "e6c3",
      "unicode_decimal": 59075
    },
    {
      "icon_id": "5326991",
      "name": "菜单",
      "font_class": "caidan3",
      "unicode": "e695",
      "unicode_decimal": 59029
    },
    {
      "icon_id": "5355323",
      "name": "锁定",
      "font_class": "suoding",
      "unicode": "e66c",
      "unicode_decimal": 58988
    },
    {
      "icon_id": "5364593",
      "name": "菜单",
      "font_class": "caidan4",
      "unicode": "e66a",
      "unicode_decimal": 58986
    },
    {
      "icon_id": "5393122",
      "name": "男",
      "font_class": "nan4",
      "unicode": "e6c6",
      "unicode_decimal": 59078
    },
    {
      "icon_id": "5517325",
      "name": "手机",
      "font_class": "shouji4",
      "unicode": "e69d",
      "unicode_decimal": 59037
    },
    {
      "icon_id": "5540389",
      "name": "撤回",
      "font_class": "chehui1",
      "unicode": "e661",
      "unicode_decimal": 58977
    },
    {
      "icon_id": "5540517",
      "name": "成功",
      "font_class": "chenggong2",
      "unicode": "e699",
      "unicode_decimal": 59033
    },
    {
      "icon_id": "5586587",
      "name": "上传",
      "font_class": "shangchuan5",
      "unicode": "e71a",
      "unicode_decimal": 59162
    },
    {
      "icon_id": "5598622",
      "name": "组件",
      "font_class": "zujian2",
      "unicode": "e7e9",
      "unicode_decimal": 59369
    },
    {
      "icon_id": "5598719",
      "name": "撤回",
      "font_class": "chehui2",
      "unicode": "ea53",
      "unicode_decimal": 59987
    },
    {
      "icon_id": "5600521",
      "name": "请假",
      "font_class": "qingjia2",
      "unicode": "e675",
      "unicode_decimal": 58997
    },
    {
      "icon_id": "5667959",
      "name": "编辑",
      "font_class": "bianji4",
      "unicode": "e71b",
      "unicode_decimal": 59163
    },
    {
      "icon_id": "5675598",
      "name": "火",
      "font_class": "huo",
      "unicode": "e71c",
      "unicode_decimal": 59164
    },
    {
      "icon_id": "5722002",
      "name": "半星",
      "font_class": "star-line",
      "unicode": "e624",
      "unicode_decimal": 58916
    },
    {
      "icon_id": "5941206",
      "name": "个人基本信息",
      "font_class": "gerenjibenxinxi",
      "unicode": "e70b",
      "unicode_decimal": 59147
    },
    {
      "icon_id": "5961142",
      "name": "耳机",
      "font_class": "erji1",
      "unicode": "e71d",
      "unicode_decimal": 59165
    },
    {
      "icon_id": "6043493",
      "name": "菜单",
      "font_class": "menu-two",
      "unicode": "e66b",
      "unicode_decimal": 58987
    },
    {
      "icon_id": "6079939",
      "name": "撤回",
      "font_class": "chehui3",
      "unicode": "e662",
      "unicode_decimal": 58978
    },
    {
      "icon_id": "6147287",
      "name": "踩",
      "font_class": "zan3",
      "unicode": "e6b8",
      "unicode_decimal": 59064
    },
    {
      "icon_id": "6154720",
      "name": "男",
      "font_class": "nan5",
      "unicode": "e6c8",
      "unicode_decimal": 59080
    },
    {
      "icon_id": "6191854",
      "name": "除法器",
      "font_class": "chufaqi",
      "unicode": "e6c4",
      "unicode_decimal": 59076
    },
    {
      "icon_id": "6289892",
      "name": "qq",
      "font_class": "qq2",
      "unicode": "e65b",
      "unicode_decimal": 58971
    },
    {
      "icon_id": "6296014",
      "name": "提示",
      "font_class": "ziyuan",
      "unicode": "e688",
      "unicode_decimal": 59016
    },
    {
      "icon_id": "6310711",
      "name": "锁",
      "font_class": "locked2",
      "unicode": "e64f",
      "unicode_decimal": 58959
    },
    {
      "icon_id": "6341926",
      "name": "半星",
      "font_class": "star-blk",
      "unicode": "e625",
      "unicode_decimal": 58917
    },
    {
      "icon_id": "6389084",
      "name": "男",
      "font_class": "nan6",
      "unicode": "e6c9",
      "unicode_decimal": 59081
    },
    {
      "icon_id": "6390131",
      "name": "男",
      "font_class": "nan7",
      "unicode": "e6ca",
      "unicode_decimal": 59082
    },
    {
      "icon_id": "6431877",
      "name": "用户",
      "font_class": "yonghu4",
      "unicode": "e64c",
      "unicode_decimal": 58956
    },
    {
      "icon_id": "6504350",
      "name": "雪花",
      "font_class": "xuehua2",
      "unicode": "e6e0",
      "unicode_decimal": 59104
    },
    {
      "icon_id": "6576586",
      "name": "新东方-刷新图标",
      "font_class": "refresh",
      "unicode": "e67c",
      "unicode_decimal": 59004
    },
    {
      "icon_id": "6669341",
      "name": "耳机",
      "font_class": "erji2",
      "unicode": "e71e",
      "unicode_decimal": 59166
    },
    {
      "icon_id": "6678999",
      "name": "qq",
      "font_class": "qq3",
      "unicode": "e643",
      "unicode_decimal": 58947
    },
    {
      "icon_id": "6706645",
      "name": "恢复",
      "font_class": "huifu",
      "unicode": "e67f",
      "unicode_decimal": 59007
    },
    {
      "icon_id": "6726694",
      "name": "用户锁定",
      "font_class": "user-locked",
      "unicode": "e763",
      "unicode_decimal": 59235
    },
    {
      "icon_id": "6739895",
      "name": "wifi",
      "font_class": "wifi",
      "unicode": "e71f",
      "unicode_decimal": 59167
    },
    {
      "icon_id": "6861713",
      "name": "踩",
      "font_class": "cai1",
      "unicode": "e6b9",
      "unicode_decimal": 59065
    },
    {
      "icon_id": "6871073",
      "name": "水",
      "font_class": "shui2",
      "unicode": "e720",
      "unicode_decimal": 59168
    },
    {
      "icon_id": "6871596",
      "name": "提示 蓝色",
      "font_class": "tishilanse",
      "unicode": "e689",
      "unicode_decimal": 59017
    },
    {
      "icon_id": "6893861",
      "name": "提示",
      "font_class": "tishi11",
      "unicode": "e68a",
      "unicode_decimal": 59018
    },
    {
      "icon_id": "6910438",
      "name": "意见箱",
      "font_class": "yijianxiang",
      "unicode": "e602",
      "unicode_decimal": 58882
    },
    {
      "icon_id": "6937863",
      "name": "女",
      "font_class": "nv2",
      "unicode": "e6cc",
      "unicode_decimal": 59084
    },
    {
      "icon_id": "6950781",
      "name": "位置",
      "font_class": "weizhi4",
      "unicode": "e721",
      "unicode_decimal": 59169
    },
    {
      "icon_id": "6966030",
      "name": "位置",
      "font_class": "weizhi5",
      "unicode": "e722",
      "unicode_decimal": 59170
    },
    {
      "icon_id": "7017192",
      "name": "锁",
      "font_class": "unlocked-blue",
      "unicode": "e63b",
      "unicode_decimal": 58939
    },
    {
      "icon_id": "7024231",
      "name": "选择分页内容图标",
      "font_class": "selected",
      "unicode": "e613",
      "unicode_decimal": 58899
    },
    {
      "icon_id": "7025307",
      "name": "选择分页内容图标",
      "font_class": "unselected",
      "unicode": "e614",
      "unicode_decimal": 58900
    },
    {
      "icon_id": "7026284",
      "name": "提示",
      "font_class": "tishi12",
      "unicode": "e68b",
      "unicode_decimal": 59019
    },
    {
      "icon_id": "7035617",
      "name": "提示",
      "font_class": "tishi13",
      "unicode": "e68c",
      "unicode_decimal": 59020
    },
    {
      "icon_id": "7054550",
      "name": "新建事件单—刷新",
      "font_class": "shuaxin3",
      "unicode": "ea29",
      "unicode_decimal": 59945
    },
    {
      "icon_id": "7088355",
      "name": "加载",
      "font_class": "jiazai4",
      "unicode": "e723",
      "unicode_decimal": 59171
    },
    {
      "icon_id": "7166079",
      "name": "用户修改",
      "font_class": "user-modify-blue",
      "unicode": "e64d",
      "unicode_decimal": 58957
    },
    {
      "icon_id": "7193681",
      "name": "组件",
      "font_class": "zujian3",
      "unicode": "e730",
      "unicode_decimal": 59184
    },
    {
      "icon_id": "7261746",
      "name": "雪花",
      "font_class": "xuehua3",
      "unicode": "e697",
      "unicode_decimal": 59031
    },
    {
      "icon_id": "7308628",
      "name": "提示",
      "font_class": "tishi14",
      "unicode": "e68d",
      "unicode_decimal": 59021
    },
    {
      "icon_id": "7342783",
      "name": "上传",
      "font_class": "shangchuan6",
      "unicode": "e724",
      "unicode_decimal": 59172
    },
    {
      "icon_id": "7380808",
      "name": "隐藏",
      "font_class": "yincangicon",
      "unicode": "e725",
      "unicode_decimal": 59173
    },
    {
      "icon_id": "7381440",
      "name": "男",
      "font_class": "nan8",
      "unicode": "e6cd",
      "unicode_decimal": 59085
    },
    {
      "icon_id": "7414164",
      "name": "位置",
      "font_class": "weizhi6",
      "unicode": "e726",
      "unicode_decimal": 59174
    },
    {
      "icon_id": "7465925",
      "name": "退出登录",
      "font_class": "tuichudenglu",
      "unicode": "e65e",
      "unicode_decimal": 58974
    },
    {
      "icon_id": "7474222",
      "name": "停止",
      "font_class": "stop1",
      "unicode": "e727",
      "unicode_decimal": 59175
    },
    {
      "icon_id": "7481739",
      "name": "锁",
      "font_class": "locked-blue",
      "unicode": "e63c",
      "unicode_decimal": 58940
    },
    {
      "icon_id": "7509805",
      "name": "上传",
      "font_class": "shangchuan7",
      "unicode": "e728",
      "unicode_decimal": 59176
    },
    {
      "icon_id": "7540496",
      "name": "未锁定",
      "font_class": "locked1",
      "unicode": "e63d",
      "unicode_decimal": 58941
    },
    {
      "icon_id": "7544188",
      "name": "刷新",
      "font_class": "shuaxin5",
      "unicode": "e656",
      "unicode_decimal": 58966
    },
    {
      "icon_id": "7624645",
      "name": "请假",
      "font_class": "qingjia-copy",
      "unicode": "e600",
      "unicode_decimal": 58880
    },
    {
      "icon_id": "7649713",
      "name": "分页向左",
      "font_class": "paging-left",
      "unicode": "e615",
      "unicode_decimal": 58901
    },
    {
      "icon_id": "7653426",
      "name": "请假",
      "font_class": "qingjia3",
      "unicode": "e6df",
      "unicode_decimal": 59103
    },
    {
      "icon_id": "7699862",
      "name": "货币管理",
      "font_class": "huobiguanli",
      "unicode": "e729",
      "unicode_decimal": 59177
    },
    {
      "icon_id": "7775923",
      "name": "系统",
      "font_class": "xitong-shixin-blk",
      "unicode": "e61e",
      "unicode_decimal": 58910
    },
    {
      "icon_id": "7806438",
      "name": "雪花",
      "font_class": "snowflake",
      "unicode": "e6ab",
      "unicode_decimal": 59051
    },
    {
      "icon_id": "7854993",
      "name": "提示",
      "font_class": "tishi15",
      "unicode": "e6dc",
      "unicode_decimal": 59100
    },
    {
      "icon_id": "7959846",
      "name": "提示",
      "font_class": "tishi16",
      "unicode": "e738",
      "unicode_decimal": 59192
    },
    {
      "icon_id": "7960443",
      "name": "水",
      "font_class": "zhishifufeiqiapianicon-",
      "unicode": "e72a",
      "unicode_decimal": 59178
    },
    {
      "icon_id": "8014774",
      "name": "加载",
      "font_class": "jiazai5",
      "unicode": "e72b",
      "unicode_decimal": 59179
    },
    {
      "icon_id": "8016321",
      "name": "女",
      "font_class": "nv3",
      "unicode": "e6ce",
      "unicode_decimal": 59086
    },
    {
      "icon_id": "8091974",
      "name": "菜单-实色",
      "font_class": "menu-s",
      "unicode": "e66d",
      "unicode_decimal": 58989
    },
    {
      "icon_id": "8118283",
      "name": "恢复",
      "font_class": "huifu1",
      "unicode": "e663",
      "unicode_decimal": 58979
    },
    {
      "icon_id": "8186234",
      "name": "减",
      "font_class": "jian2",
      "unicode": "e6ad",
      "unicode_decimal": 59053
    },
    {
      "icon_id": "8308774",
      "name": "图片下载",
      "font_class": "tupianxiazai1",
      "unicode": "e72c",
      "unicode_decimal": 59180
    },
    {
      "icon_id": "8325197",
      "name": "菜单",
      "font_class": "csm-memu",
      "unicode": "e671",
      "unicode_decimal": 58993
    },
    {
      "icon_id": "8333871",
      "name": "2019",
      "font_class": "2019",
      "unicode": "e666",
      "unicode_decimal": 58982
    },
    {
      "icon_id": "8368798",
      "name": "女",
      "font_class": "nv4",
      "unicode": "e6cf",
      "unicode_decimal": 59087
    },
    {
      "icon_id": "8414310",
      "name": "火",
      "font_class": "fire-o",
      "unicode": "e72d",
      "unicode_decimal": 59181
    },
    {
      "icon_id": "8544691",
      "name": "提示",
      "font_class": "tishi17",
      "unicode": "e68e",
      "unicode_decimal": 59022
    },
    {
      "icon_id": "8552231",
      "name": "微博",
      "font_class": "weibo1",
      "unicode": "e6c5",
      "unicode_decimal": 59077
    },
    {
      "icon_id": "8656883",
      "name": "未锁定",
      "font_class": "unlocked1",
      "unicode": "e63e",
      "unicode_decimal": 58942
    },
    {
      "icon_id": "8661817",
      "name": "组件",
      "font_class": "zujian4",
      "unicode": "e72e",
      "unicode_decimal": 59182
    },
    {
      "icon_id": "8676529",
      "name": "链接",
      "font_class": "lianjie4",
      "unicode": "e72f",
      "unicode_decimal": 59183
    },
    {
      "icon_id": "8740108",
      "name": "半星",
      "font_class": "star-orange",
      "unicode": "e626",
      "unicode_decimal": 58918
    },
    {
      "icon_id": "8745377",
      "name": "恢复",
      "font_class": "huifu2",
      "unicode": "e664",
      "unicode_decimal": 58980
    },
    {
      "icon_id": "8791483",
      "name": "提示",
      "font_class": "tishi18",
      "unicode": "e68f",
      "unicode_decimal": 59023
    },
    {
      "icon_id": "8797448",
      "name": "组件",
      "font_class": "sub-unit",
      "unicode": "e732",
      "unicode_decimal": 59186
    },
    {
      "icon_id": "8854627",
      "name": "手机",
      "font_class": "shouji5",
      "unicode": "e65c",
      "unicode_decimal": 58972
    },
    {
      "icon_id": "8860448",
      "name": "菜单",
      "font_class": "caidan5",
      "unicode": "e79b",
      "unicode_decimal": 59291
    },
    {
      "icon_id": "8894439",
      "name": "系统",
      "font_class": "xitong3",
      "unicode": "e61f",
      "unicode_decimal": 58911
    },
    {
      "icon_id": "8912145",
      "name": "货币",
      "font_class": "huobi3",
      "unicode": "e733",
      "unicode_decimal": 59187
    },
    {
      "icon_id": "8942609",
      "name": "购物车-23",
      "font_class": "qicheqianlian-1-copy",
      "unicode": "e734",
      "unicode_decimal": 59188
    },
    {
      "icon_id": "8960926",
      "name": "系统",
      "font_class": "xitong-kongxin-blue",
      "unicode": "e620",
      "unicode_decimal": 58912
    },
    {
      "icon_id": "8979849",
      "name": "验证码 密码",
      "font_class": "yanzhengmamima",
      "unicode": "e670",
      "unicode_decimal": 58992
    },
    {
      "icon_id": "9018317",
      "name": "耳机",
      "font_class": "erji3",
      "unicode": "e735",
      "unicode_decimal": 59189
    },
    {
      "icon_id": "9070580",
      "name": "火",
      "font_class": "huo1",
      "unicode": "e736",
      "unicode_decimal": 59190
    },
    {
      "icon_id": "9114466",
      "name": "系统",
      "font_class": "xitong-kongxin-blk",
      "unicode": "e62e",
      "unicode_decimal": 58926
    },
    {
      "icon_id": "9178547",
      "name": "女",
      "font_class": "nv5",
      "unicode": "e6d0",
      "unicode_decimal": 59088
    },
    {
      "icon_id": "9179545",
      "name": "提示",
      "font_class": "tishi19",
      "unicode": "e690",
      "unicode_decimal": 59024
    },
    {
      "icon_id": "9305144",
      "name": "失败",
      "font_class": "shibai3",
      "unicode": "e713",
      "unicode_decimal": 59155
    },
    {
      "icon_id": "9322729",
      "name": "分页向右",
      "font_class": "paging-right",
      "unicode": "e630",
      "unicode_decimal": 58928
    },
    {
      "icon_id": "9346255",
      "name": "暂停 停止",
      "font_class": "zantingtingzhi",
      "unicode": "e737",
      "unicode_decimal": 59191
    },
    {
      "icon_id": "9366720",
      "name": "女",
      "font_class": "nv6",
      "unicode": "e6d2",
      "unicode_decimal": 59090
    },
    {
      "icon_id": "9392579",
      "name": "男",
      "font_class": "nan9",
      "unicode": "e6d3",
      "unicode_decimal": 59091
    },
    {
      "icon_id": "9399102",
      "name": "提 示",
      "font_class": "tishi20",
      "unicode": "e691",
      "unicode_decimal": 59025
    },
    {
      "icon_id": "9415569",
      "name": "播放",
      "font_class": "bofang",
      "unicode": "e739",
      "unicode_decimal": 59193
    },
    {
      "icon_id": "9445042",
      "name": "菜单",
      "font_class": "menu1",
      "unicode": "e672",
      "unicode_decimal": 58994
    },
    {
      "icon_id": "9466230",
      "name": "耳机",
      "font_class": "erji4",
      "unicode": "e73a",
      "unicode_decimal": 59194
    },
    {
      "icon_id": "9482422",
      "name": "上传",
      "font_class": "shangchuan8",
      "unicode": "e73b",
      "unicode_decimal": 59195
    },
    {
      "icon_id": "9523967",
      "name": "停止",
      "font_class": "tingzhi2",
      "unicode": "e73c",
      "unicode_decimal": 59196
    },
    {
      "icon_id": "9577828",
      "name": "下载",
      "font_class": "xiazai",
      "unicode": "e73d",
      "unicode_decimal": 59197
    },
    {
      "icon_id": "9678810",
      "name": "提示",
      "font_class": "tishi21",
      "unicode": "e692",
      "unicode_decimal": 59026
    },
    {
      "icon_id": "9720607",
      "name": "阅读",
      "font_class": "yuedu2",
      "unicode": "e73e",
      "unicode_decimal": 59198
    },
    {
      "icon_id": "9756409",
      "name": "分页 - 下一页",
      "font_class": "fenye-xiayiye",
      "unicode": "e617",
      "unicode_decimal": 58903
    },
    {
      "icon_id": "9772642",
      "name": "星星",
      "font_class": "star-blue",
      "unicode": "e627",
      "unicode_decimal": 58919
    },
    {
      "icon_id": "9881373",
      "name": "女",
      "font_class": "nv7",
      "unicode": "e6d4",
      "unicode_decimal": 59092
    },
    {
      "icon_id": "9916482",
      "name": "百分号",
      "font_class": "baifenhao1",
      "unicode": "e6ae",
      "unicode_decimal": 59054
    },
    {
      "icon_id": "9923634",
      "name": "搜索--1",
      "font_class": "m-search",
      "unicode": "e740",
      "unicode_decimal": 59200
    },
    {
      "icon_id": "9947326",
      "name": "雪花",
      "font_class": "xuehua4",
      "unicode": "e731",
      "unicode_decimal": 59185
    },
    {
      "icon_id": "10049685",
      "name": "用户-新增",
      "font_class": "add-user2",
      "unicode": "e650",
      "unicode_decimal": 58960
    },
    {
      "icon_id": "10051665",
      "name": "货币",
      "font_class": "huobi4",
      "unicode": "e741",
      "unicode_decimal": 59201
    },
    {
      "icon_id": "10054479",
      "name": "水",
      "font_class": "shui3",
      "unicode": "e742",
      "unicode_decimal": 59202
    },
    {
      "icon_id": "10070862",
      "name": "菜单",
      "font_class": "caidan6",
      "unicode": "e673",
      "unicode_decimal": 58995
    },
    {
      "icon_id": "10096285",
      "name": "系统",
      "font_class": "xitong-shixin-blue",
      "unicode": "e621",
      "unicode_decimal": 58913
    },
    {
      "icon_id": "10115831",
      "name": "分页2",
      "font_class": "right-border",
      "unicode": "e62a",
      "unicode_decimal": 58922
    },
    {
      "icon_id": "10116115",
      "name": "分页1",
      "font_class": "left-border",
      "unicode": "e637",
      "unicode_decimal": 58935
    },
    {
      "icon_id": "10140597",
      "name": "QQ",
      "font_class": "QQ",
      "unicode": "e792",
      "unicode_decimal": 59282
    },
    {
      "icon_id": "10141469",
      "name": "验证码",
      "font_class": "yanzhengma-",
      "unicode": "e636",
      "unicode_decimal": 58934
    },
    {
      "icon_id": "10157635",
      "name": "验证码 密码",
      "font_class": "yanzhengmamima1",
      "unicode": "e638",
      "unicode_decimal": 58936
    },
    {
      "icon_id": "10163993",
      "name": "火",
      "font_class": "huo2",
      "unicode": "e743",
      "unicode_decimal": 59203
    },
    {
      "icon_id": "10164277",
      "name": "男",
      "font_class": "nan10",
      "unicode": "e6d5",
      "unicode_decimal": 59093
    },
    {
      "icon_id": "10169726",
      "name": "耳机",
      "font_class": "erji5",
      "unicode": "e744",
      "unicode_decimal": 59204
    },
    {
      "icon_id": "10220584",
      "name": "眼睛",
      "font_class": "yanjing1",
      "unicode": "e745",
      "unicode_decimal": 59205
    },
    {
      "icon_id": "10220725",
      "name": "验证码",
      "font_class": "yanzhengma6",
      "unicode": "e639",
      "unicode_decimal": 58937
    },
    {
      "icon_id": "10221541",
      "name": "成功",
      "font_class": "chenggong3",
      "unicode": "e69b",
      "unicode_decimal": 59035
    },
    {
      "icon_id": "10228573",
      "name": "提示",
      "font_class": "tishi22",
      "unicode": "e693",
      "unicode_decimal": 59027
    },
    {
      "icon_id": "10238485",
      "name": "钻石",
      "font_class": "zuanshi4",
      "unicode": "e746",
      "unicode_decimal": 59206
    },
    {
      "icon_id": "10252114",
      "name": "播放",
      "font_class": "bofang1",
      "unicode": "e78d",
      "unicode_decimal": 59277
    },
    {
      "icon_id": "10273259",
      "name": "下载",
      "font_class": "xiazai1",
      "unicode": "e747",
      "unicode_decimal": 59207
    },
    {
      "icon_id": "10281771",
      "name": "播放",
      "font_class": "bofang2",
      "unicode": "e748",
      "unicode_decimal": 59208
    },
    {
      "icon_id": "10295707",
      "name": "下载",
      "font_class": "xiazai2",
      "unicode": "e749",
      "unicode_decimal": 59209
    },
    {
      "icon_id": "10300676",
      "name": "加",
      "font_class": "jia3",
      "unicode": "e6af",
      "unicode_decimal": 59055
    },
    {
      "icon_id": "10307045",
      "name": "成功",
      "font_class": "chenggong4",
      "unicode": "e69a",
      "unicode_decimal": 59034
    },
    {
      "icon_id": "10353660",
      "name": "搜索",
      "font_class": "sousuo1",
      "unicode": "e74a",
      "unicode_decimal": 59210
    },
    {
      "icon_id": "10356990",
      "name": "上传",
      "font_class": "shangchuan9",
      "unicode": "e74b",
      "unicode_decimal": 59211
    },
    {
      "icon_id": "10369063",
      "name": "下载",
      "font_class": "download-01",
      "unicode": "e74c",
      "unicode_decimal": 59212
    },
    {
      "icon_id": "10414362",
      "name": "菜单",
      "font_class": "caidan7",
      "unicode": "e674",
      "unicode_decimal": 58996
    },
    {
      "icon_id": "10415586",
      "name": "下载",
      "font_class": "download",
      "unicode": "e74d",
      "unicode_decimal": 59213
    },
    {
      "icon_id": "10418265",
      "name": "上传",
      "font_class": "shangchuan10",
      "unicode": "e823",
      "unicode_decimal": 59427
    },
    {
      "icon_id": "10428880",
      "name": "刷新",
      "font_class": "shuaxin4",
      "unicode": "e65d",
      "unicode_decimal": 58973
    },
    {
      "icon_id": "10440986",
      "name": "成功",
      "font_class": "chenggong5",
      "unicode": "e69c",
      "unicode_decimal": 59036
    },
    {
      "icon_id": "10481155",
      "name": "分页 下一页",
      "font_class": "pagerprev-blk",
      "unicode": "e618",
      "unicode_decimal": 58904
    },
    {
      "icon_id": "10484945",
      "name": "下载",
      "font_class": "xiazai3",
      "unicode": "e74e",
      "unicode_decimal": 59214
    },
    {
      "icon_id": "10533301",
      "name": "分 享",
      "font_class": "fenxiang1",
      "unicode": "e74f",
      "unicode_decimal": 59215
    },
    {
      "icon_id": "10538938",
      "name": "组件",
      "font_class": "zujian5",
      "unicode": "e966",
      "unicode_decimal": 59750
    },
    {
      "icon_id": "10616815",
      "name": "雪花",
      "font_class": "snow-btn",
      "unicode": "e678",
      "unicode_decimal": 59000
    },
    {
      "icon_id": "10688398",
      "name": "提 示",
      "font_class": "tishi23",
      "unicode": "e696",
      "unicode_decimal": 59030
    },
    {
      "icon_id": "10720070",
      "name": "编辑 (1)",
      "font_class": "bianji5",
      "unicode": "e750",
      "unicode_decimal": 59216
    },
    {
      "icon_id": "10792640",
      "name": "新增角色用户_新增新建操作_jurassic",
      "font_class": "add-user",
      "unicode": "e6ed",
      "unicode_decimal": 59117
    },
    {
      "icon_id": "10884339",
      "name": "水",
      "font_class": "shui4",
      "unicode": "e751",
      "unicode_decimal": 59217
    },
    {
      "icon_id": "10908104",
      "name": "验证码",
      "font_class": "yanzhengma7",
      "unicode": "e67b",
      "unicode_decimal": 59003
    },
    {
      "icon_id": "10950684",
      "name": "分页 - 下一页",
      "font_class": "fenye-shangyiye1",
      "unicode": "e619",
      "unicode_decimal": 58905
    },
    {
      "icon_id": "11020695",
      "name": "乘",
      "font_class": "cheng2",
      "unicode": "e6b1",
      "unicode_decimal": 59057
    },
    {
      "icon_id": "11175971",
      "name": "菜单",
      "font_class": "caidan-",
      "unicode": "e703",
      "unicode_decimal": 59139
    },
    {
      "icon_id": "11493140",
      "name": "上 传",
      "font_class": "shangchuan11",
      "unicode": "e752",
      "unicode_decimal": 59218
    },
    {
      "icon_id": "11789299",
      "name": "半星",
      "font_class": "star-half-orange",
      "unicode": "e629",
      "unicode_decimal": 58921
    },
    {
      "icon_id": "11791522",
      "name": "购物车",
      "font_class": "che",
      "unicode": "e753",
      "unicode_decimal": 59219
    },
    {
      "icon_id": "11797461",
      "name": "流程查询",
      "font_class": "liuchengchaxun",
      "unicode": "e608",
      "unicode_decimal": 58888
    },
    {
      "icon_id": "11847959",
      "name": "QQ--",
      "font_class": "QQ-blue",
      "unicode": "ea22",
      "unicode_decimal": 59938
    },
    {
      "icon_id": "11894908",
      "name": "购物车-23",
      "font_class": "qicheqianlian-",
      "unicode": "e754",
      "unicode_decimal": 59220
    },
    {
      "icon_id": "12057602",
      "name": "编 辑",
      "font_class": "bianji6",
      "unicode": "e755",
      "unicode_decimal": 59221
    },
    {
      "icon_id": "12075637",
      "name": "半星",
      "font_class": "star-half-red",
      "unicode": "e62b",
      "unicode_decimal": 58923
    },
    {
      "icon_id": "12095848",
      "name": "编 辑",
      "font_class": "bianji7",
      "unicode": "e757",
      "unicode_decimal": 59223
    },
    {
      "icon_id": "12236073",
      "name": "常用流程",
      "font_class": "changyongliucheng",
      "unicode": "e694",
      "unicode_decimal": 59028
    },
    {
      "icon_id": "12434376",
      "name": "分页 - 下一页",
      "font_class": "fenye-shangyiye11",
      "unicode": "e61a",
      "unicode_decimal": 58906
    },
    {
      "icon_id": "12465678",
      "name": "用户修改",
      "font_class": "yonghuxiugai2",
      "unicode": "e651",
      "unicode_decimal": 58961
    },
    {
      "icon_id": "12467874",
      "name": "分页 - 下一页",
      "font_class": "fenye-xiayiye2",
      "unicode": "e61b",
      "unicode_decimal": 58907
    },
    {
      "icon_id": "12491672",
      "name": "用户删除",
      "font_class": "user-del",
      "unicode": "e652",
      "unicode_decimal": 58962
    },
    {
      "icon_id": "12532831",
      "name": "分 享",
      "font_class": "fenxiang2",
      "unicode": "e758",
      "unicode_decimal": 59224
    }
  ]
}
